picnic/__init__.py
picnic/picnic.py
picnic/util.py
picnic_python-0.2.0.dist-info/DESCRIPTION.rst
picnic_python-0.2.0.dist-info/METADATA
picnic_python-0.2.0.dist-info/metadata.json
picnic_python-0.2.0.dist-info/RECORD
picnic_python-0.2.0.dist-info/top_level.txt
picnic_python-0.2.0.dist-info/WHEEL
