Metadata-Version: 2.0
Name: picnic-python
Version: 0.2.0
Summary: Picnic API Python client library
Home-page: https://github.com/ketchupinc/picnic-python
Author: Hans E Hyttinen
Author-email: h@ketchup.is
License: MIT
Keywords: development picnic.sh
Platform: UNKNOWN
Classifier: Development Status :: 3 - Alpha
Classifier: Intended Audience :: Developers
Classifier: Topic :: Software Development :: Libraries :: Python Modules
Classifier: License :: OSI Approved :: MIT License
Classifier: Programming Language :: Python
Classifier: Programming Language :: Python :: 2
Classifier: Programming Language :: Python :: 2.7
Classifier: Programming Language :: Python :: 3
Classifier: Programming Language :: Python :: 3.2
Classifier: Programming Language :: Python :: 3.3
Classifier: Programming Language :: Python :: 3.4
Requires-Dist: requests
